odoo/addons/survey_resource_booking/README.rst
odoo/addons/survey_resource_booking/__init__.py
odoo/addons/survey_resource_booking/__manifest__.py
odoo/addons/survey_resource_booking/i18n/es.po
odoo/addons/survey_resource_booking/i18n/fr.po
odoo/addons/survey_resource_booking/i18n/fr_CH.po
odoo/addons/survey_resource_booking/i18n/it.po
odoo/addons/survey_resource_booking/i18n/survey_resource_booking.pot
odoo/addons/survey_resource_booking/models/__init__.py
odoo/addons/survey_resource_booking/models/resource_booking.py
odoo/addons/survey_resource_booking/models/resource_booking_type.py
odoo/addons/survey_resource_booking/readme/CONTRIBUTORS.md
odoo/addons/survey_resource_booking/readme/DESCRIPTION.md
odoo/addons/survey_resource_booking/readme/ROADMAP.md
odoo/addons/survey_resource_booking/readme/USAGE.md
odoo/addons/survey_resource_booking/static/description/icon.png
odoo/addons/survey_resource_booking/static/description/index.html
odoo/addons/survey_resource_booking/tests/__init__.py
odoo/addons/survey_resource_booking/tests/test_invite.py
odoo/addons/survey_resource_booking/views/resource_booking_type_views.xml
odoo/addons/survey_resource_booking/views/resource_booking_views.xml
odoo_addon_survey_resource_booking-17.0.1.0.0.2.dist-info/METADATA
odoo_addon_survey_resource_booking-17.0.1.0.0.2.dist-info/WHEEL
odoo_addon_survey_resource_booking-17.0.1.0.0.2.dist-info/top_level.txt
odoo_addon_survey_resource_booking-17.0.1.0.0.2.dist-info/RECORD
